autosub/__init__.py
autosub/constants.py
autosub/formatters.py
autosubmaia-0.0.1.dist-info/LICENSE
autosubmaia-0.0.1.dist-info/METADATA
autosubmaia-0.0.1.dist-info/WHEEL
autosubmaia-0.0.1.dist-info/entry_points.txt
autosubmaia-0.0.1.dist-info/top_level.txt
autosubmaia-0.0.1.dist-info/RECORD
