Metadata-Version: 2.1
Name: autosubmaia
Version: 0.0.1
Summary: Auto-generates subtitles for any video or audio file with support to wit.ai and speech recognition module.
Home-page: https://github.com/Iucasmaia/autosub
Author: Lucas Maia
Author-email: lucasmaia.contato@icloud.com
License: The MIT License (MIT)        
Platform: UNKNOWN
License-File: LICENSE
Requires-Dist: google-api-python-client (>=1.4.2)
Requires-Dist: requests (>=2.3.0)
Requires-Dist: pysrt (>=1.0.1)
Requires-Dist: progressbar2 (>=3.34.3)
Requires-Dist: six (>=1.11.0)
Requires-Dist: SpeechRecognition (>=3.8.1)
